{"note":"This file is an internal implementation detail to speed up HTML report generation. Its format can change at any time. You might be looking for the JSON report: https://coverage.rtfd.io/cmd.html#cmd-json","format":2,"version":"7.4.1","globals":"e9319f49c8842c734b29719599e32da7","files":{"d_9df13ddeb1e47e46___init___py":{"hash":"e6baa73cda2916dad605215f937a92e1","index":{"nums":[0,1,0,0,0,0,0,0],"html_filename":"d_9df13ddeb1e47e46___init___py.html","relative_filename":"pages/__init__.py"}},"d_9df13ddeb1e47e46_basic_auth_py":{"hash":"5ba9d3666d8b64c545771f02d8250a4c","index":{"nums":[0,1,27,0,3,0,0,0],"html_filename":"d_9df13ddeb1e47e46_basic_auth_py.html","relative_filename":"pages/basic_auth.py"}},"d_9df13ddeb1e47e46_home_page_py":{"hash":"4ad6e0aa3361c58f9c2b7a0f7f0899bf","index":{"nums":[0,1,9,0,2,0,0,0],"html_filename":"d_9df13ddeb1e47e46_home_page_py.html","relative_filename":"pages/home_page.py"}},"tasks_py":{"hash":"d4b0d846596374e1bca7e40f8b4ed812","index":{"nums":[0,1,15,0,15,0,0,0],"html_filename":"tasks_py.html","relative_filename":"tasks.py"}},"d_a44f0ac069e85531_conftest_py":{"hash":"01154812f41d6e099cf4298c6475d410","index":{"nums":[0,1,21,0,2,0,0,0],"html_filename":"d_a44f0ac069e85531_conftest_py.html","relative_filename":"tests/conftest.py"}},"d_a56771ee3a49906e_test_basic_auth_bdd_py":{"hash":"17eab6bcd74948551fcad68393396013","index":{"nums":[0,1,27,0,0,0,0,0],"html_filename":"d_a56771ee3a49906e_test_basic_auth_bdd_py.html","relative_filename":"tests/steps/test_basic_auth_bdd.py"}},"d_a56771ee3a49906e_test_home_page_bdd_py":{"hash":"bc2976faf96b48a5ccbd07c6a2a6a3ce","index":{"nums":[0,1,15,0,4,0,0,0],"html_filename":"d_a56771ee3a49906e_test_home_page_bdd_py.html","relative_filename":"tests/steps/test_home_page_bdd.py"}}}}